shopyo/.test.prod.env
shopyo/CHANGELOG.md
shopyo/__init__.py
shopyo/__main__.py
shopyo/app.py
shopyo/app.txt
shopyo/autoapp.py.example
shopyo/config.py
shopyo/init.py
shopyo/manage.py
shopyo/shopyo_admin.py
shopyo/wsgi.py.example
shopyo/__pycache__/__init__.cpython-314.pyc
shopyo/api/__init__.py
shopyo/api/assets.py
shopyo/api/cli.py
shopyo/api/cli_content.py
shopyo/api/cmd.py
shopyo/api/cmd_helper.py
shopyo/api/constants.py
shopyo/api/database.py
shopyo/api/debug.py
shopyo/api/email.py
shopyo/api/endpoint.py
shopyo/api/enhance.py
shopyo/api/file.py
shopyo/api/forms.py
shopyo/api/html.py
shopyo/api/icons.txt
shopyo/api/info.py
shopyo/api/models.py
shopyo/api/module.py
shopyo/api/response.py
shopyo/api/security.py
shopyo/api/templates.py
shopyo/api/validators.py
shopyo/api/tests/__init__.py
shopyo/api/tests/conftest.py
shopyo/api/tests/test_assets.py
shopyo/api/tests/test_cli.py
shopyo/api/tests/test_cmd.py
shopyo/api/tests/test_cmd_helper.py
shopyo/api/tests/test_constants.py
shopyo/api/tests/test_database.py
shopyo/api/tests/test_debug.py
shopyo/api/tests/test_email.py
shopyo/api/tests/test_endpoint.py
shopyo/api/tests/test_enhance.py
shopyo/api/tests/test_file.py
shopyo/api/tests/test_forms.py
shopyo/api/tests/test_html.py
shopyo/api/tests/test_info.py
shopyo/api/tests/test_initialise.py
shopyo/api/tests/test_models.py
shopyo/api/tests/test_module.py
shopyo/api/tests/test_response.py
shopyo/api/tests/test_security.py
shopyo/api/tests/test_templates.py
shopyo/api/tests/test_validators.py
shopyo/modules/__init__.py
shopyo/modules/box__tests/box_info.json
shopyo/modules/box__tests/test1/forms.py
shopyo/modules/box__tests/test1/global.py
shopyo/modules/box__tests/test1/info.json
shopyo/modules/box__tests/test1/models.py
shopyo/modules/box__tests/test1/view.py
shopyo/modules/box__tests/test1/static/file.css
shopyo/modules/box__tests/test1/templates/test1/dashboard.html
shopyo/modules/box__tests/test1/templates/test1/blocks/sidebar.html
shopyo-4.15.0.dist-info/licenses/LICENSE
shopyo-4.15.0.dist-info/METADATA
shopyo-4.15.0.dist-info/WHEEL
shopyo-4.15.0.dist-info/entry_points.txt
shopyo-4.15.0.dist-info/top_level.txt
shopyo-4.15.0.dist-info/RECORD
