Metadata-Version: 2.4
Name: shopyo
Version: 4.15.0
Summary: Highly modular web framework built for big apps on top of Flask with Django advantages
Home-page: https://github.com/shopyo/shopyo
Author: Abdur-Rahmaan Janhangeer
Author-email: arj.python@gmail.com
License: MIT
Project-URL: Source Code, https://github.com/shopyo/shopyo/
Project-URL: Issue Tracker, https://github.com/shopyo/shopyo/issues/
Project-URL: Changelog, https://github.com/shopyo/shopyo/blob/dev/CHANGES.md/
Project-URL: Twitter, https://twitter.com/shopyoproject/
Keywords: Flask,Django,web framework,modular
Classifier: Environment :: Web Environment
Classifier: Programming Language :: Python :: 3
Classifier: Programming Language :: Python :: 3.7
Classifier: Programming Language :: Python :: 3.8
Classifier: Programming Language :: Python :: 3.9
Classifier: Programming Language :: Python :: 3.10
Classifier: Programming Language :: Python :: 3.11
Classifier: Programming Language :: Python :: 3.12
Classifier: Programming Language :: Python :: 3.13
Classifier: License :: OSI Approved :: MIT License
Classifier: Operating System :: OS Independent
Classifier: Intended Audience :: Developers
Classifier: Development Status :: 4 - Beta
Requires-Python: >=3.6
License-File: LICENSE
Requires-Dist: Flask>=2.0.2
Requires-Dist: Flask-Admin>=1.5.8
Requires-Dist: Flask-Login>=0.5.0
Requires-Dist: flask-mailman>=0.3.0
Requires-Dist: Flask-Migrate>=3.1.0
Requires-Dist: Flask-SQLAlchemy>=2.5.1
Requires-Dist: Flask-WTF>=1.0.0
Requires-Dist: SQLAlchemy>=1.4.27
Requires-Dist: Werkzeug>=2.0.2
Requires-Dist: WTForms>=3.0.0
Requires-Dist: email-validator
Requires-Dist: importlib-metadata; python_version < "3.8"
Dynamic: home-page
Dynamic: license-file
Dynamic: requires-dist
